{
  "Library": "_Varistor",
  "Reference": "F",
  "Symbol": "Device:Varistor",
  "Value": "MOV-20D471K",
  "Footprint": "Varistor:RV_Disc_D21.5mm_W5.8mm_P10mm",
  "Description": "Varistor, Continuous Voltage: 300VAC, Clamping Voltage: 775V",
  "Datasheet": "https://www.bourns.com/docs/Product-Datasheets/MOV20D.pdf",
  "Keywords": "Varistor",
  "CustomFields": {
    "MF": "Mouser",
    "MPN": "MOV-20D471K",
    "OC_CONRAD": "",
    "OC_FARNELL": "",
    "OC_LCSC": "C1531018",
    "OC_MOUSER": "652-MOV-20D471K",
    "OC_REICHELT": ""
  }
}